awsquery/__init__.py
awsquery/cli.py
awsquery/config.py
awsquery/core.py
awsquery/default_filters.yaml
awsquery/filters.py
awsquery/formatters.py
awsquery/policy.json
awsquery/security.py
awsquery/utils.py
awsquery-0.4.0.dist-info/licenses/LICENSE
awsquery-0.4.0.dist-info/METADATA
awsquery-0.4.0.dist-info/WHEEL
awsquery-0.4.0.dist-info/entry_points.txt
awsquery-0.4.0.dist-info/top_level.txt
awsquery-0.4.0.dist-info/RECORD
